mondrian_maker/__init__.py
mondrian_maker/mondrian.py
tests/__init__.py
tests/test_mondrian_maker.py
mondrian_maker-0.0.2.dist-info/LICENSE
mondrian_maker-0.0.2.dist-info/METADATA
mondrian_maker-0.0.2.dist-info/WHEEL
mondrian_maker-0.0.2.dist-info/top_level.txt
mondrian_maker-0.0.2.dist-info/RECORD
