Metadata-Version: 2.1
Name: mondrian-maker
Version: 0.0.2
Summary: Python package that produces randomly-generated Mondrian-style plots
Home-page: https://github.com/andrewbowen19/mondrian-maker
Author: Andrew Bowen
Author-email: atbowen@gmail.com
License: GNU General Public License v2.0
Keywords: example documentation tutorial
Platform: UNKNOWN
